field_compression_benchmark-0.0.15.dist-info/METADATA
field_compression_benchmark-0.0.15.dist-info/RECORD
field_compression_benchmark-0.0.15.dist-info/top_level.txt
field_compression_benchmark-0.0.15.dist-info/WHEEL
field_compression_benchmark-0.0.15.dist-info/LICENSE-APACHE
field_compression_benchmark-0.0.15.dist-info/LICENSE-MIT
fcbench/__init__.py
fcbench/_fcbench.cpython-312-x86_64-linux-gnu.so
fcbench/data/codecs/linear-quantize.wasm
fcbench/data/codecs/random-projection.wasm
fcbench/data/codecs/swizzle-reshape.wasm
fcbench/data/codecs/wasmtime.toml
fcbench/data/codecs/zstd.wasm
fcbench/data/codecs/fourier-network.wasm
fcbench/data/codecs/zfp.wasm
fcbench/data/codecs/identity.wasm
fcbench/data/codecs/uniform-noise.wasm
fcbench/data/codecs/fixed-offset-scale.wasm
fcbench/data/codecs/asinh.wasm
fcbench/data/codecs/bit-round.wasm
fcbench/data/codecs/round.wasm
fcbench/data/codecs/reinterpret.wasm
fcbench/data/codecs/sz3.wasm
fcbench/data/codecs/log.wasm
fcbench/data/codecs/zlib.wasm
fcbench/metrics/__init__.py
fcbench/codecs/__init__.py
fcbench/compressor/types.py
fcbench/compressor/__init__.py
fcbench/model/types.py
fcbench/model/__init__.py
fcbench/benchmark/types.py
fcbench/benchmark/__init__.py
fcbench/dataset/types.py
fcbench/dataset/__init__.py
