Metadata-Version: 2.1
Name: field-compression-benchmark
Version: 0.0.15
Summary: Data compression methods and benchmarks for Cli/Met datasets
Author-email: Juniper Tyree <juniper.tyree@helsinki.fi>
Maintainer-email: Juniper Tyree <juniper.tyree@helsinki.fi>
License:                                  Apache License
Classifier: Programming Language :: Rust
Classifier: Programming Language :: Python :: Implementation :: CPython
Classifier: Programming Language :: Python :: Implementation :: PyPy
Requires-Python: >=3.10
License-File: LICENSE-APACHE
License-File: LICENSE-MIT
